impressive_strawberry/database/alembic/env.py
impressive_strawberry/database/alembic/script.py.mako
impressive_strawberry/database/alembic/versions/00755101936c_add_achievement_token.py
impressive_strawberry/database/alembic/versions/02aa20f04fa4_add_webhook_type.py
impressive_strawberry/database/alembic/versions/28bba5deeda4_add_obtainable_to_achievements.py
impressive_strawberry/database/alembic/versions/713b76b25d40_first_revision.py
impressive_strawberry/database/alembic/versions/b33f0ec71a4b_fix_webhook_column_name.py
impressive_strawberry/database/alembic/versions/cddef8d2958d_rename_obtainable_to_unlockable.py
impressive_strawberry/database/alembic/versions/e8df1cc27545_move_webhooks_to_their_own_table.py
impressive_strawberry/database/alembic/versions/f2eff2e29545_add_achievement_crystal.py
impressive_strawberry/database/engine.py
impressive_strawberry/database/tables.py
impressive_strawberry/web/__main__.py
impressive_strawberry/web/app.py
impressive_strawberry/web/crud/__init__.py
impressive_strawberry/web/deps/__init__.py
impressive_strawberry/web/deps/achievement.py
impressive_strawberry/web/deps/application.py
impressive_strawberry/web/deps/database.py
impressive_strawberry/web/deps/group.py
impressive_strawberry/web/deps/impressive.py
impressive_strawberry/web/deps/unlock.py
impressive_strawberry/web/deps/user.py
impressive_strawberry/web/deps/webhook.py
impressive_strawberry/web/description.md
impressive_strawberry/web/errors/__init__.py
impressive_strawberry/web/handlers/__init__.py
impressive_strawberry/web/models/__init__.py
impressive_strawberry/web/models/base.py
impressive_strawberry/web/models/edit.py
impressive_strawberry/web/models/error.py
impressive_strawberry/web/models/full.py
impressive_strawberry/web/models/read.py
impressive_strawberry/web/responses/__init__.py
impressive_strawberry/web/responses/raw.py
impressive_strawberry/web/routes/api/achievement/v1/router.py
impressive_strawberry/web/routes/api/application/v1/router.py
impressive_strawberry-0.4.2.dist-info/entry_points.txt
impressive_strawberry-0.4.2.dist-info/LICENSE.txt
impressive_strawberry-0.4.2.dist-info/METADATA
impressive_strawberry-0.4.2.dist-info/WHEEL
impressive_strawberry-0.4.2.dist-info/RECORD
